[
    {
        "question": "1 + 1 等于几？",
        "options": ["1", "2", "3", "4"],
        "answer": "2"
    },
    {
        "question": "太阳从哪里升起？",
        "options": ["北", "南", "东", "西"],
        "answer": "东"
    },
    {
        "question": "地球上最大的动物是什么？",
        "options": ["大象", "蓝鲸", "恐龙", "长颈鹿"],
        "answer": "蓝鲸"
    },
    {
        "question": "一年有多少天？",
        "options": ["365", "366", "364", "360"],
        "answer": "365"
    },
    {
        "question": "中国的首都是哪里？",
        "options": ["上海", "广州", "北京", "深圳"],
        "answer": "北京"
    },
    {
        "question": "水的沸点是多少摄氏度？",
        "options": ["50", "100", "150", "200"],
        "answer": "100"
    },
    {
        "question": "世界上最长的河流是？",
        "options": ["亚马逊河", "尼罗河", "长江", "密西西比河"],
        "answer": "尼罗河"
    },
    {
        "question": "人类有多少颗牙齿？",
        "options": ["28", "30", "32", "36"],
        "answer": "32"
    },
    {
        "question": "企鹅生活在南极还是北极？",
        "options": ["南极", "北极"],
        "answer": "南极"
    },
    {
        "question": "彩虹有几种颜色？",
        "options": ["5", "6", "7", "8"],
        "answer": "7"
    },
    {
        "question": "中国的国庆节是几月几日？",
        "options": ["9月1日", "10月1日", "11月1日", "12月1日"],
        "answer": "10月1日"
    },
    {
        "question": "世界上最高的山是？",
        "options": ["珠穆朗玛峰", "乔戈里峰", "干城章嘉峰", "洛子峰"],
        "answer": "珠穆朗玛峰"
    },
    {
        "question": "人类的心脏有几个腔？",
        "options": ["2", "3", "4", "5"],
        "answer": "4"
    },
    {
        "question": "中国的国旗有几颗星星？",
        "options": ["4", "5", "6", "7"],
        "answer": "5"
    },
    {
        "question": "地球有几个大洲？",
        "options": ["5", "6", "7", "8"],
        "answer": "7"
    },
    {
        "question": "世界上最深的海沟是？",
        "options": ["马里亚纳海沟", "汤加海沟", "菲律宾海沟", "日本海沟"],
        "answer": "马里亚纳海沟"
    },
    {
        "question": "人类的正常体温是多少摄氏度？",
        "options": ["35", "36.5", "37", "38"],
        "answer": "37"
    },
    {
        "question": "中国的第一大河是？",
        "options": ["黄河", "长江", "珠江", "松花江"],
        "answer": "长江"
    },
    {
        "question": "世界上最大的沙漠是？",
        "options": ["撒哈拉沙漠", "戈壁沙漠", "塔克拉玛干沙漠", "大维多利亚沙漠"],
        "answer": "撒哈拉沙漠"
    },
    {
        "question": "人类的大脑分为几个主要部分？",
        "options": ["2", "3", "4", "5"],
        "answer": "3"
    },
    {
        "question": "中国的传统节日春节一般在几月？",
        "options": ["1月", "2月", "3月", "4月"],
        "answer": "1月"
    },
    {
        "question": "世界上最小的国家是？",
        "options": ["梵蒂冈", "摩纳哥", "列支敦士登", "圣马力诺"],
        "answer": "梵蒂冈"
    },
    {
        "question": "人类的血液是什么颜色的？",
        "options": ["红色", "蓝色", "绿色", "黄色"],
        "answer": "红色"
    },
    {
        "question": "中国的四大发明不包括以下哪一项？",
        "options": ["指南针", "火药", "造纸术", "印刷术", "蒸汽机"],
        "answer": "蒸汽机"
    },
    {
        "question": "太阳系中最大的行星是？",
        "options": ["地球", "火星", "木星", "土星"],
        "answer": "木星"
    },
    {
        "question": "人类的骨骼总数是多少？",
        "options": ["200", "206", "210", "220"],
        "answer": "206"
    },
    {
        "question": "中国的国歌是？",
        "options": ["义勇军进行曲", "黄河大合唱", "歌唱祖国", "我的祖国"],
        "answer": "义勇军进行曲"
    },
    {
        "question": "世界上最长的城墙是？",
        "options": ["长城", "柏林墙", "万里长城", "金门大桥"],
        "answer": "长城"
    },
    {
        "question": "人类的血型分为几种主要类型？",
        "options": ["2", "3", "4", "5"],
        "answer": "4"
    },
    {
        "question": "中国的传统节日端午节吃什么？",
        "options": ["饺子", "月饼", "粽子", "汤圆"],
        "answer": "粽子"
    },
    {
        "question": "世界上最冷的地方是？",
        "options": ["南极", "北极", "西伯利亚", "格陵兰"],
        "answer": "南极"
    },
    {
        "question": "人类的眼睛有几种颜色？",
        "options": ["1", "2", "3", "多种"],
        "answer": "多种"
    },
    {
        "question": "中国的传统节日中秋节吃什么？",
        "options": ["饺子", "月饼", "粽子", "汤圆"],
        "answer": "月饼"
    },
    {
        "question": "世界上最古老的文字是？",
        "options": ["甲骨文", "楔形文字", "象形文字", "拉丁文"],
        "answer": "楔形文字"
    },
    {
        "question": "人类的耳朵有几个部分？",
        "options": ["2", "3", "4", "5"],
        "answer": "3"
    },
    {
        "question": "中国的传统节日元宵节吃什么？",
        "options": ["饺子", "月饼", "粽子", "汤圆"],
        "answer": "汤圆"
    },
    {
        "question": "世界上最热的地方是？",
        "options": ["撒哈拉沙漠", "死亡谷", "澳大利亚", "印度"],
        "answer": "死亡谷"
    },
    {
        "question": "人类的皮肤有几层？",
        "options": ["1", "2", "3", "4"],
        "answer": "3"
    },
    {
        "question": "中国的传统节日清明节做什么？",
        "options": ["扫墓", "吃粽子", "赏月", "放烟花"],
        "answer": "扫墓"
    },
    {
        "question": "世界上最深的湖是？",
        "options": ["贝加尔湖", "里海", "苏必利尔湖", "维多利亚湖"],
        "answer": "贝加尔湖"
    },
    {
        "question": "人类的头发每天大约长多少毫米？",
        "options": ["0.1", "0.3", "0.5", "1"],
        "answer": "0.3"
    },
    {
        "question": "中国的传统节日重阳节做什么？",
        "options": ["登高", "吃粽子", "赏月", "放烟花"],
        "answer": "登高"
    },
    {
        "question": "世界上最大的岛屿是？",
        "options": ["格陵兰岛", "马达加斯加岛", "新几内亚岛", "日本"],
        "answer": "格陵兰岛"
    },
    {
        "question": "人类的指甲每月大约长多少毫米？",
        "options": ["1", "2", "3", "4"],
        "answer": "3"
    },
    {
        "question": "中国的传统节日七夕节与什么有关？",
        "options": ["牛郎织女", "嫦娥奔月", "龙舟竞渡", "扫墓"],
        "answer": "牛郎织女"
    },
    {
        "question": "世界上最小的海是？",
        "options": ["波罗的海", "地中海", "红海", "马尔马拉海"],
        "answer": "马尔马拉海"
    }
]